{"dependencies":[{"name":"/home/szamulko/Desktop/Projects/PacMan/package.json","includedInParent":true,"mtime":1528724217926},{"name":"/home/szamulko/Desktop/Projects/PacMan/node_modules/@tensorflow/tfjs-layers/package.json","includedInParent":true,"mtime":1528724212618},{"name":"@tensorflow/tfjs-core","loc":{"line":1,"column":30}},{"name":"../utils/generic_utils","loc":{"line":2,"column":39}}],"generated":{"js":"'use strict';\n\nObject.defineProperty(exports, \"__esModule\", {\n    value: true\n});\nexports.deserialize = deserialize;\n\nvar _tfjsCore = require('@tensorflow/tfjs-core');\n\nvar _generic_utils = require('../utils/generic_utils');\n\nfunction deserialize(config, customObjects) {\n    if (customObjects === void 0) {\n        customObjects = {};\n    }\n    return (0, _generic_utils.deserializeKerasObject)(config, _tfjsCore.serialization.SerializationMap.getMap().classNameMap, customObjects, 'layer');\n}\n//# sourceMappingURL=serialization.js.map"},"hash":"05f6401d4c608f25aa1cc3f58db1fe7f","cacheData":{"env":{}}}